[
  {
    "id": 1,
    "task": "Ahmednor"
  },
  {
    "id": 2,
    "task": "Cali"
  },
  {
    "id": 1697693663757,
    "task": "baable"
  },
  {
    "id": 1697695163897,
    "task": "test"
  },
  {
    "id": 1697696466442,
    "task": "cumar cali"
  },
  {
    "id": 1697696620238,
    "task": "test"
  },
  {
    "id": 1697696720230,
    "task": "tijaabo"
  },
  {
    "id": 1697697663111,
    "task": "clear"
  },
  {
    "id": 1697736977739,
    "task": "reading"
  },
  {
    "id": 1697737014485,
    "task": "ali"
  },
  {
    "id": 1697737164816,
    "task": "reading"
  },
  {
    "id": 1697737606105,
    "task": "farah"
  },
  {
    "id": 1697737632232,
    "task": "Abdijabar"
  }
]